ChiSquareTestForString/__init__.py
ChiSquareTestForString-0.0.1.dist-info/METADATA
ChiSquareTestForString-0.0.1.dist-info/WHEEL
ChiSquareTestForString-0.0.1.dist-info/top_level.txt
ChiSquareTestForString-0.0.1.dist-info/RECORD
