Metadata-Version: 2.1
Name: ChiSquareTestForString
Version: 0.0.1
Summary: Chi-Square Test for string columns
Home-page: UNKNOWN
Author: Sasan Sharifipour
Author-email: <sasansharifipour@email.com>
License: UNKNOWN
Keywords: python,pyspark,ChiSquareTest,ChiSquareTestForString
Platform: UNKNOWN
Classifier: Development Status :: 3 - Alpha
Classifier: Programming Language :: Python :: 3
Classifier: Operating System :: Microsoft :: Windows
Requires-Dist: pyspark
